{
  "schemaVersion": 1,
  "id": "preserve_physics_to_map_projection_contracts",
  "title": "Preserve Physics To Map Projection Contracts",
  "placement": {
    "niche": "civ7/mapgen/map-output",
    "blueprint": "_remainder",
    "category": "contract",
    "artifactKind": "check"
  },
  "ownerProject": "mod-swooper-maps",
  "lane": "enforced",
  "forbids": "physics contracts requiring map artifacts/effects, realized-map artifact tags, or non-canonical map effect names",
  "why": "The physics-to-map projection seam is a contract boundary, not package-local behavior.",
  "remediate": null,
  "message": "Keep map projection dependencies on the map side of the contract seam.",
  "pathCoverage": [
    {
      "kind": "exact-path",
      "patterns": [
        "mods/mod-swooper-maps/src/recipes/standard/stages/**/*.contract.ts",
        "mods/mod-swooper-maps/src/**/*.ts",
        "packages/mapgen-core/src/**/*.ts"
      ]
    }
  ],
  "artifacts": {
    "baseline": ".habitat/civ7/mapgen/map-output/_remainder/preserve_physics_to_map_projection_contracts/baseline.json"
  },
  "runner": {
    "name": "habitat",
    "mode": "script",
    "runtime": "node",
    "files": {
      "script": ".habitat/civ7/mapgen/map-output/_remainder/preserve_physics_to_map_projection_contracts/check.mjs"
    }
  }
}
